aider_lint_fixer/__init__.py
aider_lint_fixer/__main__.py
aider_lint_fixer/aider_integration.py
aider_lint_fixer/aider_strategic_recommendations.py
aider_lint_fixer/ast_dependency_analyzer.py
aider_lint_fixer/cache_cli.py
aider_lint_fixer/community_issue_reporter.py
aider_lint_fixer/config_manager.py
aider_lint_fixer/context_manager.py
aider_lint_fixer/control_flow_analyzer.py
aider_lint_fixer/convergence_analyzer.py
aider_lint_fixer/cost_monitor.py
aider_lint_fixer/enhanced_interactive.py
aider_lint_fixer/error_analyzer.py
aider_lint_fixer/intelligent_force_mode.py
aider_lint_fixer/iterative_force_mode.py
aider_lint_fixer/lint_runner.py
aider_lint_fixer/main.py
aider_lint_fixer/native_lint_detector.py
aider_lint_fixer/pattern_matcher.py
aider_lint_fixer/pre_lint_assessment.py
aider_lint_fixer/progress_tracker.py
aider_lint_fixer/project_detector.py
aider_lint_fixer/rule_scraper.py
aider_lint_fixer/smart_linter_selector.py
aider_lint_fixer/strategic_preflight_check.py
aider_lint_fixer/structural_analyzer.py
aider_lint_fixer/supported_versions.py
aider_lint_fixer/linters/__init__.py
aider_lint_fixer/linters/ansible_lint.py
aider_lint_fixer/linters/base.py
aider_lint_fixer/linters/eslint_linter.py
aider_lint_fixer/linters/flake8_linter.py
aider_lint_fixer/linters/jshint_linter.py
aider_lint_fixer/linters/prettier_linter.py
aider_lint_fixer/linters/pylint_linter.py
aider_lint_fixer-2.0.3.dist-info/METADATA
aider_lint_fixer-2.0.3.dist-info/WHEEL
aider_lint_fixer-2.0.3.dist-info/entry_points.txt
aider_lint_fixer-2.0.3.dist-info/top_level.txt
aider_lint_fixer-2.0.3.dist-info/RECORD
