Metadata-Version: 2.4
Name: aider-lint-fixer
Version: 2.0.3
Summary: AI-powered lint error detection and fixing using aider.chat
Home-page: https://github.com/tosin2023/aider-lint-fixer
Author: Tosin Akinosho
Author-email: Aider Lint Fixer Team <tosin@decisioncrafters.com>
License: MIT
Project-URL: Homepage, https://github.com/tosin2013/aider-lint-fixer
Project-URL: Repository, https://github.com/tosin2013/aider-lint-fixer
Project-URL: Issues, https://github.com/tosin2013/aider-lint-fixer/issues
Project-URL: Documentation, https://github.com/tosin2013/aider-lint-fixer/blob/main/README.md
Classifier: Development Status :: 4 - Beta
Classifier: Intended Audience :: Developers
Classifier: License :: OSI Approved :: MIT License
Classifier: Operating System :: OS Independent
Classifier: Programming Language :: Python :: 3
Classifier: Programming Language :: Python :: 3.11
Classifier: Programming Language :: Python :: 3.12
Classifier: Topic :: Software Development :: Quality Assurance
Classifier: Topic :: Software Development :: Testing
Requires-Python: >=3.8
Requires-Dist: aider-chat>=0.82.0
Requires-Dist: click>=8.0.0
Requires-Dist: colorama>=0.4.0
Requires-Dist: pyyaml>=6.0.0
Requires-Dist: pathlib2>=2.3.0; python_version < "3.4"
Provides-Extra: dev
Requires-Dist: pytest>=7.0.0; extra == "dev"
Requires-Dist: pytest-cov>=4.0.0; extra == "dev"
Requires-Dist: pytest-mock>=3.10.0; extra == "dev"
Requires-Dist: black>=23.0.0; extra == "dev"
Requires-Dist: isort>=5.12.0; extra == "dev"
Requires-Dist: flake8>=6.0.0; extra == "dev"
Requires-Dist: mypy>=1.0.0; extra == "dev"
Requires-Dist: pre-commit>=3.0.0; extra == "dev"
Requires-Dist: coverage>=7.0.0; extra == "dev"
Requires-Dist: mock>=4.0.0; extra == "dev"
Requires-Dist: responses>=0.23.0; extra == "dev"
Provides-Extra: linters
Requires-Dist: flake8>=7.3.0; extra == "linters"
Requires-Dist: pylint>=3.3.0; extra == "linters"
Requires-Dist: ansible-lint>=25.6.0; extra == "linters"
Provides-Extra: learning
Requires-Dist: scikit-learn>=1.0.0; extra == "learning"
Requires-Dist: requests>=2.25.0; extra == "learning"
Requires-Dist: beautifulsoup4>=4.9.0; extra == "learning"
Requires-Dist: pyahocorasick>=1.4.0; extra == "learning"
Provides-Extra: progress
Requires-Dist: tqdm>=4.64.0; extra == "progress"
Provides-Extra: community
Provides-Extra: all
Requires-Dist: flake8>=7.3.0; extra == "all"
Requires-Dist: pylint>=3.3.0; extra == "all"
Requires-Dist: ansible-lint>=25.6.0; extra == "all"
Requires-Dist: scikit-learn>=1.0.0; extra == "all"
Requires-Dist: requests>=2.25.0; extra == "all"
Requires-Dist: beautifulsoup4>=4.9.0; extra == "all"
Requires-Dist: pyahocorasick>=1.4.0; extra == "all"
Requires-Dist: tqdm>=4.64.0; extra == "all"
Dynamic: author
Dynamic: home-page
Dynamic: requires-python
